calculator/__init__.py
calculator/core.py
calculator_eldar_matrix-0.5.0.dist-info/licenses/LICENSE
calculator_eldar_matrix-0.5.0.dist-info/METADATA
calculator_eldar_matrix-0.5.0.dist-info/WHEEL
calculator_eldar_matrix-0.5.0.dist-info/top_level.txt
calculator_eldar_matrix-0.5.0.dist-info/RECORD
