Metadata-Version: 2.4
Name: calculator-eldar-matrix
Version: 0.5.0
Summary: Python calculator library with math, trig, stats, and geometry functions
Home-page: https://github.com/eldar/calculator
Author: Eldar
Author-email: eldar2005matrix@gmail.com
Requires-Python: >=3.12
License-File: LICENSE
Dynamic: author
Dynamic: author-email
Dynamic: home-page
Dynamic: license-file
Dynamic: requires-python
Dynamic: summary
